{
  "type": "FeatureCollection",
  "features": [
    {
      "type": "Feature",
      "geometry": {
        "type": "Point",
        "coordinates": [
          18.105389999999996,
          59.58362000000001,
          52.50000000076363
        ]
      },
      "properties": {
        "name": "huset",
        "scale": 1,
        "minimumPixelSize": 128,
        "horizontalRotation": -95,
        "verticalRotation": 0,
        "lateralRotation": 0
      }
    }
  ]
}