{
  "type": "FeatureCollection",
  "features": [
    {
      "type": "Feature",
      "geometry": {
        "type": "Point",
        "coordinates": [
          -7.087851874580446,
          7.494427378788488,
          -436.94351517908046
        ]
      },
      "properties": {
        "name": "Sem+nome",
        "scale": 1,
        "minimumPixelSize": 128,
        "horizontalRotation": 0,
        "verticalRotation": 0,
        "lateralRotation": 0
      }
    }
  ]
}